{
  "$schema": "https://biomejs.dev/schemas/1.6.0/schema.json",
  "organizeImports": {
    "enabled": true
  },
  "vcs": {
    "enabled": true,
    "clientKind": "git",
    "useIgnoreFile": true
  },
  "formatter": {
    "enabled": true,
    "formatWithErrors": false,
    "ignore": [],
    "indentStyle": "space",
    "indentWidth": 2,
    "lineWidth": 100
  },
  "json": {
    "parser": {
      "allowComments": true
    },
    "formatter": {
      "enabled": true,
      "indentStyle": "space",
      "indentWidth": 2,
      "lineWidth": 100
    }
  },
  "javascript": {
    "formatter": {
      "enabled": true,
      "quoteStyle": "single",
      "jsxQuoteStyle": "double",
      "trailingComma": "es5",
      "arrowParentheses": "always",
      "indentStyle": "space",
      "indentWidth": 2,
      "lineWidth": 100,
      "quoteProperties": "asNeeded"
    },
    "globals": ["expect", "describe", "it", "test", "jest", "beforeEach", "afterEach", "JSX"]
  },
  "linter": {
    "enabled": true,
    "rules": {
      "recommended": true,
      "correctness": {
        "noUndeclaredVariables": "error",
        "noUnusedVariables": "error",
        "useExhaustiveDependencies": "error",
        "useHookAtTopLevel": "off"
      },
      "style": {
        "noNamespace": "error"
      },
      "suspicious": {
        "noExplicitAny": "off",
        "noArrayIndexKey": "off"
      }
    }
  }
}
